{
	"info": {
		"_postman_id": "acfebbd9-27c5-4219-86ff-7ac4da96fc9a",
		"name": "Transport Management API",
		"description": "Transport Management API\n- Version: 1.0\n- Description: This is a service for manage transport vehicle\n- Host: localhost:8080\n- BasePath: /",
		"schema": "https://schema.getpostman.com/json/collection/v2.1.0/collection.json"
	},
	"item": [
		{
			"name": "api/v1",
			"item": [
				{
					"name": "vehicles",
					"item": [
						{
							"name": "GetVehicles",
							"request": {
								"method": "GET",
								"header": [],
								"url": {
									"raw": "{{baseUrl}}/vehicles",
									"host": [
										"{{baseUrl}}"
									],
									"path": [
										"vehicles"
									]
								},
								"description": "Get details of all vehicles"
							},
							"response": []
						},
						{
							"name": "GetVehicle",
							"request": {
								"method": "GET",
								"header": [],
								"url": {
									"raw": "{{baseUrl}}/vehicles/:vehicleId",
									"host": [
										"{{baseUrl}}"
									],
									"path": [
										"vehicles",
										":vehicleId"
									],
									"variable": [
										{
											"key": "vehicleId",
											"value": "",
											"description": "ID of vehicle"
										}
									]
								},
								"description": "Get details of vehicle with ID"
							},
							"response": []
						}
					]
				},
				{
					"name": "travels",
					"item": [
						{
							"name": "GetTravelHistoriesOfVehicle",
							"request": {
								"method": "GET",
								"header": [],
								"url": {
									"raw": "{{baseUrl}}/travels/:vehicleId/all",
									"host": [
										"{{baseUrl}}"
									],
									"path": [
										"travels",
										":vehicleId",
										"all"
									],
									"variable": [
										{
											"key": "vehicleId",
											"value": "610a4946c816f391280de1f5",
											"description": "ID of vehicle"
										}
									]
								},
								"description": "Get details all travel histories of vehicle"
							},
							"response": []
						},
						{
							"name": "GetTravelHistoriesVehicleWithFilter",
							"request": {
								"method": "GET",
								"header": [],
								"url": {
									"raw": "{{baseUrl}}/travels/:vehicleId/filter?month=2021-08",
									"host": [
										"{{baseUrl}}"
									],
									"path": [
										"travels",
										":vehicleId",
										"filter"
									],
									"query": [
										{
											"key": "date",
											"value": "2021-08-01",
											"description": "Filter with date (YYYY-MM-DD)",
											"disabled": true
										},
										{
											"key": "month",
											"value": "2021-08",
											"description": "Filter with month(YYYY-MM)"
										}
									],
									"variable": [
										{
											"key": "vehicleId",
											"value": "610a4946c816f391280de1f5",
											"description": "ID of vehicle"
										}
									]
								},
								"description": "Get details all travel histories of vehicle with time filter"
							},
							"response": []
						},
						{
							"name": "GetTravelHistoriesOnDate",
							"request": {
								"method": "GET",
								"header": [],
								"url": {
									"raw": "{{baseUrl}}/travels/:date",
									"host": [
										"{{baseUrl}}"
									],
									"path": [
										"travels",
										":date"
									],
									"variable": [
										{
											"key": "date",
											"value": null,
											"description": "Date (YYYY-MM-DD)"
										}
									]
								},
								"description": "Get all travel histories on date"
							},
							"response": []
						},
						{
							"name": "GetDistanceTraveled",
							"request": {
								"method": "GET",
								"header": [],
								"url": {
									"raw": "{{baseUrl}}/travels/:vehicleId/distance?date=2021-08-01&month=",
									"host": [
										"{{baseUrl}}"
									],
									"path": [
										"travels",
										":vehicleId",
										"distance"
									],
									"query": [
										{
											"key": "date",
											"value": "2021-08-01",
											"description": "Get distance traveled on Date (YYYY-MM-DD)"
										},
										{
											"key": "month",
											"value": "",
											"description": "Get distance traveled on Month (YYYY-MM)"
										}
									],
									"variable": [
										{
											"key": "vehicleId",
											"value": "610a4946c816f391280de1f5",
											"description": "ID of vehicle"
										}
									]
								},
								"description": "Get distance traveled (km) of vehicle in day"
							},
							"response": []
						},
						{
							"name": "AddTravelHistoryOfVehicle",
							"request": {
								"method": "POST",
								"header": [],
								"body": {
									"mode": "raw",
									"raw": "{\n    \"location\": {\n        \"coordinates\": [\n            1.5,\n            1.5\n        ],\n        \"type\": \"Point\"\n    },\n    \"transportId\": \"610ce5a6389bd57bf80633e2\",\n    \"updatedAt\": \"2021-08-03T12:02:00+07:00\"\n}",
									"options": {
										"raw": {
											"language": "json"
										}
									}
								},
								"url": {
									"raw": "{{baseUrl}}/travels/:vehicleId",
									"host": [
										"{{baseUrl}}"
									],
									"path": [
										"travels",
										":vehicleId"
									],
									"variable": [
										{
											"key": "vehicleId",
											"value": "610a4946c816f391280de1f5",
											"description": "Vehicle ID"
										}
									]
								},
								"description": "Add travel history of vehicle\n- body json example:\n\n{\\\n  \"location\": {\\\n     \"coordinates\": [0,0],\\\n     \"type\": \"Point\"\\\n  },\\\n  \"transportId\": \"610ce5a6389bd57bf80633e2\",\\\n  \"updatedAt\": \"2021-08-03T12:02:00+07:00\"\\\n}"
							},
							"response": []
						}
					]
				},
				{
					"name": "GetStatistics",
					"request": {
						"method": "GET",
						"header": [],
						"url": {
							"raw": "{{baseUrl}}/statistics/:vehicleId?month=2021-08",
							"host": [
								"{{baseUrl}}"
							],
							"path": [
								"statistics",
								":vehicleId"
							],
							"query": [
								{
									"key": "month",
									"value": "2021-08",
									"description": "Get statistic on month (YYYY-MM)"
								},
								{
									"key": "date",
									"value": "2021-08-01",
									"description": "Get statistic on date (YYYY-MM-DD)",
									"disabled": true
								}
							],
							"variable": [
								{
									"key": "vehicleId",
									"value": "610a4946c816f391280de1f5",
									"description": "Vehicle ID"
								}
							]
						},
						"description": "Get statistic of vehicle on time"
					},
					"response": []
				}
			]
		}
	],
	"event": [
		{
			"listen": "prerequest",
			"script": {
				"type": "text/javascript",
				"exec": [
					""
				]
			}
		},
		{
			"listen": "test",
			"script": {
				"type": "text/javascript",
				"exec": [
					""
				]
			}
		}
	],
	"variable": [
		{
			"key": "baseUrl",
			"value": "localhost:8080/api/v1"
		},
		{
			"key": "vehicles",
			"value": "localhost:8080/api/v1/vehicles"
		},
		{
			"key": "travels",
			"value": "localhost:8080/api/v1/travels"
		}
	]
}